{
  "Word": 1,
  "Support": 1,
  "Go": 1,
  "properti": 1,
  "convert": 1,
  "bit": 5,
  "Document": 1,
  "type": 1,
  "enhanc": 1,
  "cover": 1,
  "Design": 1,
  "number": 1,
  "review": 1,
  "Work": 2,
  "92": 1,
  "Websit": 1,
  "Microsoft": 1,
  "text": 1,
  "write": 2,
  "rang": 1,
  "Thing": 1,
  "Privaci": 2,
  "creat": 1,
  "edit": 1,
  "work": 3,
  "automat": 1,
  "IAB": 1,
  "manag": 2,
  "Kei": 1,
  "accept": 1,
  "Datatrack": 2,
  "How": 1,
  "London": 2,
  "Write": 5,
  "Hide": 1,
  "Group": 2,
  "Meet": 1,
  "In": 1,
  "optim": 1,
  "It": 1,
  "manual": 2,
  "polici": 1,
  "The": 1,
  "IESG": 2,
  "search": 2,
  "Thi": 2,
  "Slide": 1,
  "markdown": 6,
  "tradition": 1,
  "event": 1,
  "Protocol": 1,
  "ISOC": 1,
  "popular": 2,
  "resourc": 2,
  "Quick": 2,
  "Commun": 1,
  "editor": 1,
  "set": 1,
  "Statement": 2,
  "chair": 2,
  "Run": 1,
  "tutori": 4,
  "plaintext": 1,
  "right": 1,
  "help": 1,
  "Draft": 9,
  "IRTF": 1,
  "principl": 1,
  "Online": 1,
  "discuss": 1,
  "standard": 1,
  "New": 6,
  "Email": 3,
  "Process": 2,
  "Secretariat": 1,
  "blog": 2,
  "Creat": 1,
  "RFC": 9,
  "YAML": 5,
  "technolog": 1,
  "structur": 1,
  "Search": 7,
  "commun": 1,
  "Mission": 1,
  "Markdown": 1,
  "Tool": 3,
  "Who": 1,
  "group": 1,
  "train": 2,
  "read": 1,
  "orient": 2,
  "finicki": 1,
  "workflow": 1,
  "AMS": 1,
  "format": 2,
  "templat": 1,
  "IETF": 12,
  "list": 3,
  "kramdown": 1,
  "tool": 5,
  "About": 2,
  "Area": 1,
  "Autom": 1,
  "Intellectu": 1,
  "Internet": 12,
  "present": 1,
  "allow": 1,
  "code": 1,
  "minim": 1,
  "link": 2,
  "Standard": 1,
  "focu": 1,
  "shepherd": 1,
  "IAOC": 1,
  "network": 1,
  "WG": 2,
  "Recent": 1,
  "contributor": 1,
  "interest": 1,
  "skill": 1,
  "leadership": 1,
  "involv": 1,
  "Present": 1,
  "hard": 1,
  "Topic": 1,
  "Blog": 2,
  "Particip": 2,
  "process": 2,
  "collabor": 1,
  "wide": 1,
  "perform": 1,
  "IANA": 1,
  "transport": 1,
  "Info": 1,
  "Tutori": 1,
  "Trust": 1,
  "Contact": 2,
  "101": 2,
  "refer": 1,
  "XML": 2,
  "archiv": 2,
  "chore": 1,
  "Editor": 2
}