{
  "Server": 3,
  "STORage": 1,
  "Raw": 1,
  "String": 2,
  "CCSDS": 1,
  "tea": 1,
  "conex": 3,
  "Past": 1,
  "Consult": 1,
  "Consider": 3,
  "Implement": 3,
  "Mechan": 8,
  "Clarifi": 1,
  "BCP": 7,
  "Kuznyechik": 1,
  "0": 1,
  "2": 5,
  "AS": 1,
  "4": 2,
  "5": 1,
  "6": 1,
  "7": 2,
  "Author": 3,
  "stox": 1,
  "A": 6,
  "Bind": 1,
  "Meet": 4,
  "E": 8,
  "Statu": 1,
  "G": 1,
  "roll": 4,
  "I": 48,
  "rtcweb": 1,
  "Paus": 1,
  "HEVC": 1,
  "Prefix": 4,
  "An": 2,
  "Font": 1,
  "PKIX": 1,
  "The": 5,
  "R": 3,
  "S": 2,
  "T": 1,
  "V": 1,
  "Workshop": 1,
  "ISOC": 1,
  "Decemb": 18,
  "Path": 7,
  "Center": 2,
  "eppext": 1,
  "Internation": 2,
  "Extensibl": 3,
  "Enforcement": 2,
  "Mobil": 1,
  "Initiat": 5,
  "Submit": 1,
  "Forward": 2,
  "Topolog": 2,
  "DWDM": 2,
  "Initial": 1,
  "justfont": 1,
  "isi": 2,
  "DC": 2,
  "opsec": 1,
  "BFD": 1,
  "Email": 2,
  "Inter": 1,
  "Using": 7,
  "Provis": 1,
  "SHA": 2,
  "Global": 1,
  "payload": 3,
  "Test": 1,
  "pal": 6,
  "Provid": 3,
  "RSVP": 1,
  "Interwork": 1,
  "Optional": 1,
  "Obstacl": 1,
  "JWS": 1,
  "HTTP": 6,
  "BGP": 5,
  "Term": 1,
  "Algorithm": 4,
  "Philosophi": 1,
  "About": 1,
  "Ds": 4,
  "MP2MP": 1,
  "POSH": 1,
  "Video": 3,
  "State": 2,
  "Servic": 8,
  "OAM": 3,
  "SIP": 1,
  "Ed": 1,
  "Advanc": 1,
  "Prefer": 1,
  "Standard": 3,
  "Presenc": 2,
  "Refer": 1,
  "Shortest": 1,
  "pcp": 2,
  "Home": 3,
  "Lambda": 1,
  "619": 1,
  "Identifi": 1,
  "Report": 5,
  "SCTP": 1,
  "Info": 1,
  "Admin": 1,
  "DNA": 1,
  "Metric": 4,
  "Forc": 1,
  "Unencod": 1,
  "Harass": 1,
  "Proactiv": 1,
  "SASL": 1,
  "DNS": 5,
  "RFC7827": 1,
  "RFC7822": 1,
  "Assignment": 2,
  "RFC7820": 1,
  "RFC7821": 1,
  "Messag": 5,
  "Interfac": 1,
  "period": 5,
  "IP": 7,
  "RFC7815": 1,
  "hybi": 2,
  "RFC7816": 1,
  "Router": 4,
  "RFC7817": 1,
  "IS": 7,
  "Transpar": 5,
  "RFC7818": 1,
  "MAC": 5,
  "RFC7814": 1,
  "Datatrack": 3,
  "Some": 1,
  "Top": 1,
  "Too": 1,
  "IKEv2": 4,
  "Miss": 1,
  "Transport": 7,
  "issu": 1,
  "SRTP": 1,
  "MAP": 1,
  "Challeng": 1,
  "RFC7808": 1,
  "Hypertext": 1,
  "In": 2,
  "regext": 1,
  "RFC7809": 1,
  "RFC7804": 1,
  "RFC7807": 1,
  "Restart": 1,
  "RFC7801": 1,
  "RFC7802": 1,
  "Strengthen": 1,
  "RFC7803": 1,
  "URN": 3,
  "Signal": 3,
  "OSPFv2": 1,
  "Divers": 1,
  "Usage": 2,
  "GOST": 3,
  "Multi": 3,
  "Layer": 2,
  "Veri": 1,
  "Tunnel": 1,
  "dnsop": 4,
  "6man": 2,
  "New": 3,
  "Task": 1,
  "Random": 1,
  "pim": 1,
  "Concept": 1,
  "Experiment": 1,
  "Public": 2,
  "April": 1,
  "MEF": 1,
  "Mandatori": 1,
  "Secret": 1,
  "Realtim": 1,
  "Option": 2,
  "Valu": 1,
  "File": 1,
  "IPv6": 6,
  "IPv4": 1,
  "Encode": 2,
  "Function": 3,
  "Format": 3,
  "Monitor": 1,
  "Framework": 1,
  "High": 1,
  "Lossi": 4,
  "Strategi": 1,
  "Virtual": 3,
  "Their": 1,
  "Point": 2,
  "Applicat": 3,
  "Mail": 1,
  "PE": 2,
  "Namespac": 2,
  "228": 1,
  "Edge": 3,
  "PS": 73,
  "Cryptograph": 3,
  "Dens": 2,
  "Node": 2,
  "Document": 3,
  "Reduc": 2,
  "STP": 1,
  "Direct": 1,
  "RFC7664": 1,
  "Matter": 1,
  "RFC7667": 1,
  "Charact": 1,
  "Technic": 1,
  "Enhancement": 1,
  "Translat": 5,
  "httpauth": 1,
  "Reachabl": 2,
  "MIB": 2,
  "Mesh": 1,
  "IAB": 1,
  "RFC7657": 1,
  "Two": 3,
  "Code": 5,
  "Multipoint": 3,
  "Scenario": 1,
  "RA": 1,
  "RFC7655": 1,
  "RFC7656": 1,
  "MSRP": 1,
  "Group": 3,
  "Announcement": 2,
  "Traffic": 1,
  "EVPN": 1,
  "ConEx": 1,
  "256": 2,
  "markdown": 1,
  "Portal": 2,
  "SM": 1,
  "Protocol": 37,
  "art": 2,
  "rtg": 1,
  "Introduct": 1,
  "Statement": 4,
  "Run": 1,
  "Normal": 1,
  "TE": 2,
  "Draft": 1,
  "Terminolog": 1,
  "Curv": 1,
  "Select": 2,
  "Certif": 1,
  "mLDP": 1,
  "Cipher": 1,
  "TP": 2,
  "avtcor": 2,
  "Schema": 1,
  "Bound": 1,
  "Label": 9,
  "Explicit": 2,
  "Requir": 7,
  "Partial": 1,
  "Search": 3,
  "Non": 1,
  "Wavelength": 4,
  "Repres": 1,
  "Divis": 2,
  "Minim": 1,
  "Problem": 1,
  "Class": 1,
  "Domain": 1,
  "Wai": 8,
  "Delai": 1,
  "Us": 1,
  "Review": 1,
  "Conduct": 1,
  "System": 2,
  "WG": 3,
  "Engineer": 1,
  "Pseudo": 2,
  "avtext": 2,
  "httpbi": 2,
  "Newcom": 1,
  "Tracerout": 1,
  "Trust": 2,
  "Base": 4,
  "ospf": 3,
  "Allocat": 1,
  "RFC7836": 1,
  "GCM": 1,
  "Scope": 1,
  "Recommend": 1,
  "Filter": 1,
  "Pseudowir": 3,
  "time": 1,
  "OSPF": 3,
  "Signatur": 1,
  "Support": 4,
  "Important": 1,
  "MPL": 3,
  "Verif": 1,
  "Network": 15,
  "Work": 5,
  "SCRAM": 2,
  "Privaci": 2,
  "Pleas": 1,
  "Log": 1,
  "ICCP": 1,
  "Connect": 1,
  "Local": 1,
  "Lot": 5,
  "Locat": 1,
  "Deriv": 1,
  "Web": 3,
  "Low": 4,
  "Stabil": 1,
  "Subnet": 2,
  "Site": 2,
  "Research": 1,
  "Self": 1,
  "Span": 1,
  "Littl": 1,
  "Taxonomi": 1,
  "Encounter": 1,
  "Upcome": 1,
  "OLSRv2": 1,
  "Logic": 1,
  "curdl": 1,
  "IKE": 1,
  "Environ": 4,
  "Loss": 1,
  "ntp": 2,
  "Consumpt": 1,
  "Notif": 1,
  "Redund": 1,
  "Vocabulari": 1,
  "Type": 4,
  "Implicat": 1,
  "Flexi": 3,
  "Share": 1,
  "appsawg": 3,
  "dice": 1,
  "Uniform": 1,
  "Deprec": 1,
  "Update": 3,
  "Brief": 1,
  "xmpp": 2,
  "Mission": 1,
  "XMPP": 2,
  "Markdown": 1,
  "cellar": 1,
  "Diffserv": 1,
  "Channel": 2,
  "Media": 4,
  "Resum": 1,
  "Charter": 1,
  "Decreas": 1,
  "Leas": 1,
  "RFC7697": 1,
  "RFC7698": 1,
  "BiDirect": 1,
  "Statist": 2,
  "Profession": 1,
  "RFC7699": 1,
  "Autom": 1,
  "RFC7693": 1,
  "RFC7694": 1,
  "RFC7695": 1,
  "RFC7696": 1,
  "RFC7690": 1,
  "RFC7691": 1,
  "RFC7692": 1,
  "TCP": 2,
  "Gener": 5,
  "Multiplex": 2,
  "Exposur": 3,
  "RFC7687": 1,
  "RFC7688": 1,
  "RFC7689": 1,
  "RFC7682": 1,
  "RFC7684": 1,
  "newbi": 1,
  "RFC7680": 1,
  "lwig": 1,
  "Attribut": 3,
  "Oversight": 1,
  "Data": 6,
  "Bridg": 1,
  "RFC7679": 1,
  "Date": 2,
  "Anchor": 1,
  "RFC7677": 1,
  "Guidanc": 1,
  "XML": 1,
  "Wiki": 1,
  "RFC7670": 1,
  "Session": 3,
  "PATH": 1,
  "Procedur": 4,
  "Indicat": 1,
  "Much": 1,
  "Store": 1,
  "IPR": 2,
  "Design": 1,
  "Codec": 2,
  "preci": 2,
  "Administr": 5,
  "ICMP": 4,
  "Space": 1,
  "xml2rfc": 1,
  "ac": 1,
  "grow": 1,
  "Respons": 1,
  "Agiliti": 1,
  "Minimis": 1,
  "Separ": 1,
  "1349": 1,
  "Simpl": 1,
  "Chassi": 1,
  "Queri": 2,
  "Note": 1,
  "Transfer": 1,
  "Configur": 3,
  "RPKI": 1,
  "Link": 8,
  "Minut": 1,
  "Set": 1,
  "IRR": 1,
  "Proceed": 3,
  "Captiv": 2,
  "Nicknam": 2,
  "Multicast": 8,
  "Salt": 1,
  "IESG": 3,
  "Comparison": 2,
  "v6op": 5,
  "NomCom": 1,
  "Queue": 1,
  "Fast": 1,
  "Revis": 1,
  "dhc": 1,
  "Associat": 4,
  "Registr": 4,
  "ppsp": 1,
  "Near": 1,
  "Correct": 1,
  "meet": 3,
  "Power": 4,
  "Predict": 1,
  "Port": 6,
  "TWAMP": 3,
  "Index": 1,
  "Attachment": 1,
  "TRILL": 5,
  "RFC": 5,
  "parti": 1,
  "Dragonfli": 1,
  "Version": 5,
  "711": 1,
  "List": 5,
  "North": 1,
  "tcpm": 1,
  "bfd": 1,
  "Profil": 2,
  "Capabl": 4,
  "Semant": 1,
  "IETF": 11,
  "AES": 1,
  "Role": 1,
  "Area": 1,
  "Ethernet": 2,
  "final": 1,
  "Dual": 2,
  "PCP": 3,
  "WebRTC": 1,
  "VP8": 1,
  "ietf": 2,
  "ccamp": 5,
  "Well": 1,
  "2012": 2,
  "Complement": 2,
  "Solut": 2,
  "JSON": 1,
  "Deploy": 1,
  "IAOC": 1,
  "Field": 1,
  "VPN": 3,
  "Chang": 1,
  "TLS": 1,
  "Big": 1,
  "Identif": 2,
  "Withdraw": 1,
  "GSS": 1,
  "IANA": 2,
  "Lite": 1,
  "Deliveri": 1,
  "WebSocket": 1,
  "form": 1,
  "2016": 91,
  "2015": 43,
  "publish": 1,
  "NAT": 1,
  "Address": 5,
  "RFC7709": 1,
  "Access": 3,
  "RFC7705": 1,
  "RFC7706": 1,
  "RFC7707": 1,
  "RFC7708": 1,
  "RFC7701": 1,
  "Hash": 1,
  "RFC7702": 1,
  "Interim": 1,
  "RFC7703": 1,
  "RFC7704": 1,
  "Establish": 1,
  "kitten": 2,
  "RFC7700": 1,
  "Discuss": 1,
  "action": 1,
  "text": 1,
  "Advertis": 5,
  "Groupchat": 1,
  "Root": 2,
  "Measur": 6,
  "CMT": 1,
  "Payload": 4,
  "Train": 1,
  "Map": 3,
  "MVPN": 1,
  "IASA": 1,
  "Chair": 2,
  "Efficienc": 1,
  "Coordin": 1,
  "IPPM": 2,
  "Simul": 1,
  "sidr": 1,
  "Disclosur": 2,
  "ippm": 6,
  "Simplif": 1,
  "Replic": 1,
  "Reconnaiss": 1,
  "Improve": 1,
  "Clarif": 1,
  "Energi": 1,
  "transmiss": 1,
  "Use": 2,
  "BLAKE2": 1,
  "PIM": 1,
  "546": 1,
  "BoF": 1,
  "LAN": 1,
  "report": 1,
  "IRTF": 2,
  "Independ": 1,
  "homenet": 1,
  "Goup": 1,
  "Perform": 2,
  "receiv": 1,
  "Secretariat": 2,
  "conclud": 1,
  "Build": 1,
  "Real": 3,
  "Rout": 5,
  "Tool": 3,
  "uta": 1,
  "manet": 1,
  "Peer": 2,
  "AMS": 1,
  "Ingress": 1,
  "Sourc": 1,
  "Experienc": 1,
  "servic": 1,
  "Ping": 4,
  "Transmiss": 1,
  "updat": 4,
  "Privat": 1,
  "Kerbero": 2,
  "Detail": 1,
  "PLUS": 1,
  "Specif": 1,
  "CDNI": 1,
  "Prepar": 2,
  "bess": 4,
  "RPL": 1,
  "total": 2,
  "LDP": 1,
  "op": 1,
  "Liaison": 3,
  "Mode": 4,
  "Error": 1,
  "VPLS": 1,
  "Scale": 1,
  "cdni": 1,
  "tzdist": 3,
  "104": 1,
  "cfrg": 2,
  "WebDAV": 1,
  "Infrastructur": 1,
  "API": 2,
  "Committe": 2,
  "Track": 2,
  "01": 1,
  "03": 1,
  "Archive": 1,
  "Spars": 1,
  "Operat": 3,
  "Repli": 2,
  "LFB": 1,
  "Anycast": 1,
  "RFC7785": 1,
  "RFC7781": 1,
  "Exchang": 3,
  "RFC7782": 1,
  "RFC7783": 1,
  "RFC7784": 1,
  "RFC7780": 1,
  "LossLess": 1,
  "10": 1,
  "11": 1,
  "12": 1,
  "15": 1,
  "16": 1,
  "SIIT": 2,
  "Circuit": 1,
  "RFC7778": 1,
  "Kei": 6,
  "DHCPv6": 1,
  "Autonom": 1,
  "Paramet": 2,
  "RFC7774": 1,
  "DHCPv4": 1,
  "RFC7775": 1,
  "RFC7776": 1,
  "RFC7777": 1,
  "RFC7770": 1,
  "RFC7771": 1,
  "RFC7772": 1,
  "DTLS": 1,
  "RFC7773": 1,
  "Close": 1,
  "Effect": 1,
  "OWAMP": 3,
  "One": 6,
  "March": 37,
  "iab": 5,
  "RTO": 1,
  "RFC7767": 1,
  "RFC7768": 1,
  "MPLS": 8,
  "RFC7769": 1,
  "131": 1,
  "Secur": 10,
  "RTP": 6,
  "RFC7763": 1,
  "133": 1,
  "RFC7764": 1,
  "RFC7765": 1,
  "RFC7766": 1,
  "RFC7760": 1,
  "RFC7761": 1,
  "RFC7762": 1,
  "Team": 3,
  "Context": 2,
  "Commun": 4,
  "Call": 1,
  "34": 3,
  "Progress": 1,
  "Protect": 2,
  "storm": 1,
  "37": 1,
  "Echo": 1,
  "jose": 1,
  "Calendar": 1,
  "RFC7756": 1,
  "PRECIS": 1,
  "RFC7757": 1,
  "Januari": 24,
  "RFC7758": 1,
  "RFC7759": 1,
  "RFC7752": 1,
  "RFC7753": 1,
  "RFC7754": 1,
  "Plenari": 1,
  "RFC7755": 1,
  "RFC7750": 1,
  "STRINT": 1,
  "RFC7751": 1,
  "40": 1,
  "44": 1,
  "NETCONF": 2,
  "PRF": 1,
  "Novemb": 25,
  "RFC7749": 1,
  "Process": 2,
  "Page": 5,
  "Manag": 6,
  "Authent": 8,
  "RFC7745": 1,
  "RFC7746": 1,
  "Name": 4,
  "RFC7748": 1,
  "RFC7741": 1,
  "RFC7742": 1,
  "Last": 1,
  "RFC7743": 1,
  "RFC7744": 1,
  "RFC7740": 1,
  "Setup": 1,
  "Packet": 1,
  "Stateless": 3,
  "Program": 1,
  "Differenti": 2,
  "RFC7738": 1,
  "RFC7739": 1,
  "RFC7734": 1,
  "RFC7735": 1,
  "Larg": 1,
  "RFC7736": 1,
  "Stack": 1,
  "RFC7737": 1,
  "RFC7730": 1,
  "RFC7731": 1,
  "RFC7732": 1,
  "RFC7733": 1,
  "Softwir": 1,
  "idr": 2,
  "Internet": 8,
  "Static": 2,
  "64": 1,
  "PTB": 1,
  "Action": 1,
  "LLC": 1,
  "Legal": 2,
  "Element": 2,
  "RFC7727": 1,
  "RFC7728": 1,
  "Time": 9,
  "RFC7729": 1,
  "RFC7723": 1,
  "RFC7724": 1,
  "RFC7725": 1,
  "RFC7726": 1,
  "RFC7720": 1,
  "RFC7721": 1,
  "Control": 8,
  "Relai": 2,
  "RFC7722": 1,
  "CalDAV": 1,
  "Optimiz": 1,
  "76": 1,
  "Relat": 1,
  "Clone": 1,
  "org": 1,
  "RFC7716": 1,
  "180": 1,
  "RFC7717": 1,
  "RFC7718": 1,
  "RFC7719": 1,
  "RFC7712": 1,
  "View": 1,
  "RFC7713": 1,
  "RFC7714": 1,
  "RFC7715": 1,
  "Extension": 13,
  "RFC7710": 1,
  "trill": 5,
  "RFC7711": 1,
  "Registri": 4,
  "Editor": 2,
  "Compat": 1,
  "Check": 2,
  "Suit": 1,
  "Encryption": 2,
  "Identiti": 1,
  "Fragment": 1,
  "problem": 1,
  "Checksum": 2,
  "CURve": 1,
  "Constrain": 2,
  "ICMPv6": 1,
  "95": 1,
  "mpl": 6,
  "ForCES": 1,
  "Switch": 12,
  "Level": 1,
  "NTPv4": 1,
  "GMPLS": 3,
  "Grid": 3,
  "Migrat": 1,
  "NTP": 1,
  "Case": 1,
  "gen": 4,
  "dart": 1,
  "Chat": 1,
  "Contain": 1,
  "Mainten": 4,
  "Abstract": 1,
  "Optical": 2,
  "Subsidiari": 1,
  "Custom": 1,
  "Tag": 1,
  "Interconnect": 6,
  "Interact": 1,
  "Polici": 5,
  "simpl": 1,
  "Edu": 1,
  "Kind": 1,
  "Javascript": 1,
  "Tree": 4,
  "Stream": 3,
  "Client": 1,
  "Member": 2,
  "Anti": 1,
  "LSC": 1,
  "UDP": 2,
  "Compress": 1,
  "LSP": 6,
  "Februari": 30,
  "Revers": 1,
  "Tabl": 1,
  "Active": 11,
  "Extend": 3,
  "Resourc": 3,
  "Content": 3,
  "Block": 3,
  "Applicabl": 1,
  "Distribut": 4,
  "Elliptic": 1,
  "send": 1,
  "capport": 1,
  "Guidelin": 2,
  "week": 1,
  "Loopback": 1,
  "Congest": 4,
  "Segment": 1,
  "Multipl": 2,
  "provid": 1,
  "Zone": 3,
  "DHCP": 1,
  "Contact": 2,
  "Accompani": 1,
  "RFC7796": 1,
  "RFC7797": 1,
  "RFC7798": 1,
  "RFC7792": 1,
  "RFC7794": 1,
  "RFC7795": 1,
  "RFC7790": 1,
  "RFC7791": 1,
  "Informat": 3
}